{
  "$schema": "../icon.schema.json",
  "contributors": [
    "karsa-mistmere",
    "ericfennis",
    "jguddas"
  ],
  "use-cases": [],
  "tags": [
    "square",
    "rectangle",
    "oblique",
    "rhombus",
    "shape",
    "suit",
    "playing",
    "cards"
  ],
  "categories": [
    "shapes",
    "gaming"
  ],
  "i18n": {
    "zh": {
      "name": "菱形",
      "tags": [
        "方形",
        "矩形",
        "卡片",
        "形状"
      ],
      "categories": [
        "形状",
        "游戏"
      ]
    }
  }
}
