{
  "$schema": "../icon.schema.json",
  "use-cases": [],
  "name": "路线关闭",
  "tags": [
    "路径",
    "旅程",
    "规划师",
    "点",
    "停止",
    "车站",
    "重置",
    "清除",
    "取消",
    "关闭",
    "被阻止"
  ],
  "categories": [
    "navigation"
  ],
  "i18n": {
    "en": {
      "name": "route off",
      "tags": [
        "path",
        "journey",
        "planner",
        "points",
        "stops",
        "stations",
        "reset",
        "clear",
        "cancelled",
        "closed",
        "blocked"
      ],
      "use-cases": []
    }
  }
}
