{
  "$schema": "../icon.schema.json",
  "use-cases": [],
  "name": "行2",
  "tags": [
    "线",
    "列表",
    "队列",
    "预览",
    "面板",
    "段落",
    "平行",
    "系列",
    "分裂",
    "垂直",
    "水平的",
    "一半",
    "中心",
    "中",
    "甚至",
    "抽屉"
  ],
  "categories": [
    "layout",
    "design",
    "text"
  ],
  "aliases": [
    {
      "name": "rows",
      "deprecationReason": "alias.name",
      "deprecated": true,
      "toBeRemovedInVersion": "v1.0"
    }
  ],
  "i18n": {
    "en": {
      "name": "rows 2",
      "tags": [
        "lines",
        "list",
        "queue",
        "preview",
        "panel",
        "paragraphs",
        "parallel",
        "series",
        "split",
        "vertical",
        "horizontal",
        "half",
        "center",
        "middle",
        "even",
        "drawer"
      ],
      "use-cases": []
    }
  }
}
