{
  "$schema": "../icon.schema.json",
  "use-cases": [],
  "name": "方形笔",
  "tags": [
    "铅笔",
    "编辑",
    "改变",
    "创建",
    "画",
    "素描",
    "草稿",
    "作家",
    "写作",
    "比罗",
    "墨水",
    "标记",
    "毡尖",
    "文具",
    "艺术家"
  ],
  "categories": [
    "text"
  ],
  "aliases": [
    {
      "name": "pen-box",
      "deprecationReason": "alias.name",
      "deprecated": true,
      "toBeRemovedInVersion": "v1.0"
    },
    {
      "name": "edit",
      "deprecationReason": "alias.name",
      "deprecated": true,
      "toBeRemovedInVersion": "v1.0"
    },
    {
      "name": "pen-square",
      "deprecationReason": "alias.name",
      "deprecated": true,
      "toBeRemovedInVersion": "v1.0"
    }
  ],
  "i18n": {
    "en": {
      "name": "square pen",
      "tags": [
        "pencil",
        "edit",
        "change",
        "create",
        "draw",
        "sketch",
        "draft",
        "writer",
        "writing",
        "biro",
        "ink",
        "marker",
        "felt tip",
        "stationery",
        "artist"
      ],
      "use-cases": []
    }
  }
}
