{
  "$schema": "../icon.schema.json",
  "use-cases": [],
  "name": "便签便签关闭",
  "tags": [
    "便利贴",
    "评论",
    "注释",
    "反应",
    "备忘录",
    "提醒",
    "待办事项",
    "任务",
    "想法",
    "头脑风暴",
    "文档",
    "页面",
    "纸",
    "片材",
    "固定式",
    "办公室",
    "残疾人",
    "隐藏的",
    "静音",
    "不活跃的"
  ],
  "categories": [
    "text",
    "social"
  ],
  "i18n": {
    "en": {
      "name": "sticky note off",
      "tags": [
        "post-it",
        "comment",
        "annotation",
        "reaction",
        "memo",
        "reminder",
        "todo",
        "task",
        "idea",
        "brainstorm",
        "document",
        "page",
        "paper",
        "sheet",
        "stationary",
        "office",
        "disabled",
        "hidden",
        "mute",
        "inactive"
      ],
      "use-cases": []
    }
  }
}
