{
  "$schema": "../icon.schema.json",
  "contributors": [
    "karsa-mistmere",
    "jguddas"
  ],
  "use-cases": [],
  "name": "素食",
  "tags": [
    "动物rights"
  ],
  "categories": [
    "food-beverage",
    "sustainability"
  ],
  "i18n": {
    "en": {
      "name": "vegan",
      "tags": [
        "vegetarian",
        "fruitarian",
        "herbivorous",
        "animal rights",
        "diet"
      ],
      "categories": [
        "Food & beverage",
        "Sustainability"
      ]
    }
  }
}
