{
  "$schema": "../icon.schema.json",
  "contributors": [
    "danielbayley",
    "jguddas",
    "jamiemlaw"
  ],
  "use-cases": [],
  "tags": [
    "beach",
    "sand",
    "net",
    "holiday",
    "vacation",
    "summer",
    "soccer",
    "football",
    "futbol",
    "kick",
    "pitch",
    "goal",
    "score",
    "bounce",
    "leather",
    "wool",
    "yarn",
    "knitting",
    "sewing",
    "thread",
    "embroidery",
    "textile"
  ],
  "categories": [
    "sports",
    "gaming",
    "travel"
  ],
  "i18n": {
    "zh": {
      "name": "排球",
      "tags": [
        "目标"
      ],
      "categories": [
        "运动",
        "游戏",
        "旅行"
      ]
    }
  }
}
