{
  "$schema": "../icon.schema.json",
  "contributors": [
    "karsa-mistmere",
    "ericfennis"
  ],
  "use-cases": [],
  "tags": [
    "alcohol",
    "beverage",
    "drink",
    "glass",
    "alcohol free",
    "abstinence",
    "abstaining",
    "teetotalism",
    "allergy",
    "intolerance"
  ],
  "categories": [
    "food-beverage"
  ],
  "i18n": {
    "zh": {
      "name": "葡萄酒关闭",
      "tags": [
        "饮品",
        "玻璃杯"
      ],
      "categories": [
        "餐饮"
      ]
    }
  }
}
